steldermann_test_wheel/__init__.py
steldermann_test_wheel/example.py
steldermann_test_wheel/fd_solver.py
steldermann_test_wheel-0.1.6.dist-info/METADATA
steldermann_test_wheel-0.1.6.dist-info/WHEEL
steldermann_test_wheel-0.1.6.dist-info/RECORD
