Metadata-Version: 2.1
Name: steldermann-test-wheel
Version: 0.1.6
Summary: A simple test to ship scikit-fdiff to pyodide.
Author: ingo.steldermann
Author-email: ingo.steldermann@rwth-aachen.de
Requires-Python: >=3.6,<4.0
Classifier: Programming Language :: Python :: 3
Classifier: Programming Language :: Python :: 3.6
Classifier: Programming Language :: Python :: 3.7
Classifier: Programming Language :: Python :: 3.8
Classifier: Programming Language :: Python :: 3.9
Classifier: Programming Language :: Python :: 3.10
Classifier: Programming Language :: Python :: 3.11
Requires-Dist: scikit-fdiff (>=0.7.0,<0.8.0)
